Metadata-Version: 1.1
Name: pyssm-sca
Version: 0.2.4
Summary: Provides a simple wrapper for getting, working with, and refreshing ssm_params
Home-page: https://github.com/Tesla-SCA/pyssm
Author: Landon Mossburg
Author-email: lmossburg@tesla.com
License: UNKNOWN
Download-URL: https://github.com/Tesla-SCA/pyssm/archive/0.1.tar.gz
Platform: UNKNOWN
